mcp4mcp/__init__.py
mcp4mcp/models.py
mcp4mcp/storage.py
mcp4mcp/analyzers/__init__.py
mcp4mcp/analyzers/code_scanner.py
mcp4mcp/analyzers/similarity.py
mcp4mcp/tools/__init__.py
mcp4mcp/tools/intelligence.py
mcp4mcp/tools/state_management.py
mcp4mcp/tools/tracking.py
mcp4mcp/utils/__init__.py
mcp4mcp/utils/helpers.py
mcp4mcp-0.1.34.dist-info/METADATA
mcp4mcp-0.1.34.dist-info/WHEEL
mcp4mcp-0.1.34.dist-info/entry_points.txt
mcp4mcp-0.1.34.dist-info/top_level.txt
mcp4mcp-0.1.34.dist-info/RECORD
