Metadata-Version: 2.4
Name: mcp4mcp
Version: 0.1.34
Summary: Meta MCP Server for MCP development intelligence
Author-email: Matt Hornung <hornung.m1@gmail.com>
Project-URL: Homepage, https://github.com/hmatt1/mcp4mcp
Project-URL: Bug Reports, https://github.com/hmatt1/mcp4mcp/issues
Project-URL: Source, https://github.com/hmatt1/mcp4mcp
Classifier: Development Status :: 3 - Alpha
Classifier: Intended Audience :: Developers
Classifier: License :: CC0 1.0 Universal (CC0 1.0) Public Domain Dedication
Classifier: Programming Language :: Python :: 3
Classifier: Programming Language :: Python :: 3.11
Classifier: Programming Language :: Python :: 3.12
Classifier: Topic :: Software Development :: Libraries :: Python Modules
Requires-Python: >=3.11
Requires-Dist: fastmcp>=2.0.0
Requires-Dist: pydantic>=2.0.0
Requires-Dist: aiosqlite>=0.19.0
Provides-Extra: dev
Requires-Dist: pytest>=8.4.1; extra == "dev"
Requires-Dist: pytest-asyncio>=1.0.0; extra == "dev"
Requires-Dist: black>=24.0.0; extra == "dev"
Requires-Dist: isort>=5.13.0; extra == "dev"
Requires-Dist: mypy>=1.8.0; extra == "dev"
